glabel/__init__.py
glabel/cli.py
glabel/main.py
glabel-1.1.3b1.dist-info/METADATA
glabel-1.1.3b1.dist-info/WHEEL
glabel-1.1.3b1.dist-info/entry_points.txt
glabel-1.1.3b1.dist-info/top_level.txt
glabel-1.1.3b1.dist-info/RECORD
