Metadata-Version: 2.1
Name: glabel
Version: 1.1.3b1
Summary: FastAPI-based image classification app for annotation
Home-page: https://github.com/gaurang157/glabel
Author: Gaurang Ingle
Author-email: gaurang.ingle@gmail.com
Keywords: image-classification,annotation,fastapi
Classifier: Development Status :: 4 - Beta
Classifier: Intended Audience :: Developers
Classifier: License :: OSI Approved :: MIT License
Classifier: Programming Language :: Python :: 3.6
Classifier: Programming Language :: Python :: 3.7
Classifier: Programming Language :: Python :: 3.8
Classifier: Programming Language :: Python :: 3.9
Classifier: Programming Language :: Python :: 3.10
Classifier: Framework :: FastAPI
Requires-Python: >=3.6
Requires-Dist: fastapi (>=0.68.0)
Requires-Dist: uvicorn (>=0.15.0)
Requires-Dist: python-multipart (==0.0.9)
